pycompete/__init__.py
pycompete/_version.py
pycompete/evaluation/metrics.py
pycompete/features/transformers.py
pycompete/model_selection/cv_splitters.py
pycompete-0.0.6.dist-info/LICENSE.txt
pycompete-0.0.6.dist-info/METADATA
pycompete-0.0.6.dist-info/WHEEL
pycompete-0.0.6.dist-info/top_level.txt
pycompete-0.0.6.dist-info/RECORD
