Metadata-Version: 2.1
Name: pycompete
Version: 0.0.6
Summary: Tools to support the training and evalaution of models for the CrunchDAO project.
Author: Francis P Chmiel
License: MIT license
Keywords: crunchdao
Classifier: Programming Language :: Python :: 3
Requires-Python: >=3.7
License-File: LICENSE.txt
Requires-Dist: numpy (==1.20.3)
Requires-Dist: pandas (==1.3.4)
Requires-Dist: scikit-learn (==0.24.2)
Requires-Dist: pytest
Requires-Dist: black (==23.3.0)
